{
  "path_id": "third_party_sharing_check",
  "summary": "命中 1 个触发点；关键要素覆盖 4/4；模糊表述 1 处。",
  "items": [
    {
      "risk_point": "第三方共享或委托处理披露可能不足",
      "risk_level": "建议优化",
      "legal_basis": "待外部规范数据库补充具体依据",
      "reason": "触发主题：第三方；已识别要素：第三方身份或类别, 共享信息范围, 共享目的, 处理方式或管理要求；模糊表述：等；证据片段：向第三方提供个人信息时，将明确告知接收方名称、联系方式、处理目的、处理方式和信息类型。。",
      "suggestion": "补充第三方类别、共享范围、目的及处理方式。",
      "auto_recheck": false,
      "evidence": [
        "向第三方提供个人信息时，将明确告知接收方名称、联系方式、处理目的、处理方式和信息类型。"
      ],
      "coverage_ratio": 1.0,
      "trigger_hits": [
        "第三方"
      ],
      "missing_groups": [],
      "ambiguity_hits": [
        "等"
      ]
    }
  ]
}